arbor_process/__init__.py
arbor_process/arbor_process.py
arbor_process/gen_filtered_shuffled_chunks.py
arbor_process/gen_img_txt_pair.py
arbor_process/get_imgs.py
arbor_process/metadata_processor.py
arbor_process/plotting_func.py
arbor_process-0.1.1.dist-info/LICENSE.txt
arbor_process-0.1.1.dist-info/METADATA
arbor_process-0.1.1.dist-info/WHEEL
arbor_process-0.1.1.dist-info/top_level.txt
arbor_process-0.1.1.dist-info/RECORD
