Metadata-Version: 2.1
Name: arbor-process
Version: 0.1.1
Summary: A package for preprocessing data in the Arboretum project.
Home-page: https://github.com/baskargroup/Arboretum/tree/main/Arbor-preprocess
Author: Baskar Group
Classifier: Programming Language :: Python :: 3
Classifier: License :: OSI Approved :: MIT License
Classifier: Operating System :: OS Independent
Requires-Python: >=3.6
License-File: LICENSE.txt
Requires-Dist: aiohttp (==3.9.5)
Requires-Dist: aiosignal (==1.3.1)
Requires-Dist: async-timeout (==4.0.3)
Requires-Dist: attrs (==23.2.0)
Requires-Dist: contourpy (==1.2.1)
Requires-Dist: cramjam (==2.8.3)
Requires-Dist: cycler (==0.12.1)
Requires-Dist: fastparquet (==2024.5.0)
Requires-Dist: fonttools (==4.53.0)
Requires-Dist: frozenlist (==1.4.1)
Requires-Dist: fsspec (==2024.6.0)
Requires-Dist: idna (==3.7)
Requires-Dist: importlib-resources (==6.4.0)
Requires-Dist: kiwisolver (==1.4.5)
Requires-Dist: matplotlib (==3.9.0)
Requires-Dist: multidict (==6.0.5)
Requires-Dist: numpy (==1.26.4)
Requires-Dist: packaging (==24.1)
Requires-Dist: pandas (==2.2.2)
Requires-Dist: pillow (==10.3.0)
Requires-Dist: pyarrow (==16.1.0)
Requires-Dist: pyparsing (==3.1.2)
Requires-Dist: python-dateutil (==2.9.0.post0)
Requires-Dist: pytz (==2024.1)
Requires-Dist: seaborn (==0.13.2)
Requires-Dist: six (==1.16.0)
Requires-Dist: tqdm (==4.66.4)
Requires-Dist: tzdata (==2024.1)
Requires-Dist: yarl (==1.9.4)
Requires-Dist: zipp (==3.19.2)
